django_tableaux/__init__.py
django_tableaux/buttons.py
django_tableaux/columns.py
django_tableaux/utils.py
django_tableaux/views.py
django_tableaux/static/django_tableaux/css/django_tableaux.css
django_tableaux/static/django_tableaux/js/django_tableaux.js
django_tableaux/templates/django_tableaux/block_content.html
django_tableaux/templates/django_tableaux/bootstrap5_base.html
django_tableaux/templates/django_tableaux/tableaux.html
django_tableaux/templates/django_tableaux/toolbar.html
django_tableaux/templates/django_tableaux/basic/alert.html
django_tableaux/templates/django_tableaux/basic/block_content.html
django_tableaux/templates/django_tableaux/basic/block_head.html
django_tableaux/templates/django_tableaux/basic/block_scripts.html
django_tableaux/templates/django_tableaux/basic/button.html
django_tableaux/templates/django_tableaux/basic/cell_edit.html
django_tableaux/templates/django_tableaux/basic/cell_error.html
django_tableaux/templates/django_tableaux/basic/cell_form.html
django_tableaux/templates/django_tableaux/basic/load_more.html
django_tableaux/templates/django_tableaux/basic/modal_base.html
django_tableaux/templates/django_tableaux/basic/modal_filter.html
django_tableaux/templates/django_tableaux/basic/modal_form.html
django_tableaux/templates/django_tableaux/basic/page_link.html
django_tableaux/templates/django_tableaux/basic/render_footer.html
django_tableaux/templates/django_tableaux/basic/render_header.html
django_tableaux/templates/django_tableaux/basic/render_paginator.html
django_tableaux/templates/django_tableaux/basic/render_row.html
django_tableaux/templates/django_tableaux/basic/render_row_mobile.html
django_tableaux/templates/django_tableaux/basic/render_rows.html
django_tableaux/templates/django_tableaux/basic/render_table.html
django_tableaux/templates/django_tableaux/basic/render_table_data.html
django_tableaux/templates/django_tableaux/basic/select_checkbox.html
django_tableaux/templates/django_tableaux/basic/tableaux.html
django_tableaux-0.7.5.dist-info/licenses/LICENSE
django_tableaux-0.7.5.dist-info/WHEEL
django_tableaux-0.7.5.dist-info/METADATA
django_tableaux-0.7.5.dist-info/RECORD
