Metadata-Version: 2.4
Name: django-tableaux
Version: 0.7.5
Summary: Django tables with Advanced User eXperience
Author-email: Ian Stewart <is@iskt.co.uk>
Requires-Python: >=3.10
Classifier: License :: OSI Approved :: MIT License
License-File: LICENSE
Requires-Dist: django-bootstrap4>=22.2
Requires-Dist: django>=4.2
Requires-Dist: django-tables2>=2.4.1
Requires-Dist: django-htmx>=1.21.0
Requires-Dist: django-filter>=23.5
Requires-Dist: tablib>=3.5.0
Project-URL: Home, https://github.com/ianastewart/django_tableaux/
